basic_test_widget/__init__.py
basic_test_widget/_version.py
basic_test_widget/example.py
basic_test_widget/static/extension.js
basic_test_widget/static/index.js
basic_test_widget/static/index.js.map
basic_test_widget-0.1.0a0.data/data/etc/jupyter/nbconfig/notebook.d/basic_test_widget.json
basic_test_widget-0.1.0a0.data/data/share/jupyter/nbextensions/basic_test_widget/extension.js
basic_test_widget-0.1.0a0.data/data/share/jupyter/nbextensions/basic_test_widget/index.js
basic_test_widget-0.1.0a0.data/data/share/jupyter/nbextensions/basic_test_widget/index.js.map
basic_test_widget-0.1.0a0.dist-info/DESCRIPTION.rst
basic_test_widget-0.1.0a0.dist-info/METADATA
basic_test_widget-0.1.0a0.dist-info/RECORD
basic_test_widget-0.1.0a0.dist-info/WHEEL
basic_test_widget-0.1.0a0.dist-info/metadata.json
basic_test_widget-0.1.0a0.dist-info/top_level.txt
